session_sampling_simulator/__init__.py
session_sampling_simulator/__main__.py
session_sampling_simulator/cli.py
session_sampling_simulator/default_queries.py
session_sampling_simulator/gui.py
session_sampling_simulator/session_simulator.py
session_sampling_simulator/analysis/__init__.py
session_sampling_simulator/analysis/total_duration.py
session_sampling_simulator-0.2.1.dist-info/METADATA
session_sampling_simulator-0.2.1.dist-info/WHEEL
session_sampling_simulator-0.2.1.dist-info/entry_points.txt
session_sampling_simulator-0.2.1.dist-info/licenses/LICENSE
session_sampling_simulator-0.2.1.dist-info/RECORD
