Metadata-Version: 2.4
Name: session-sampling-simulator
Version: 0.2.1
Summary: An application/library for simulating the sampling of Postgres session states.
License-File: LICENSE
Requires-Python: >=3.12
Requires-Dist: humanize>=4.12.1
Requires-Dist: matplotlib>=3.10.1
Requires-Dist: numpy>=2.2.3
Requires-Dist: pandas>=2.2.3
Requires-Dist: pyyaml>=6.0.2
Requires-Dist: seaborn>=0.13.2
Requires-Dist: tabulate>=0.9.0
Requires-Dist: typer>=0.15.2
